{
  "id": "stepfun_220322022317",
  "date": "2026/3/10 23:21:23",
  "title": "阶跃AI对话 [Skills,邮件,提示词,开发]",
  "summary": "会话220322022317，17次工具调用，使用工具: file_system_read,email,file_system_edit,terminal_execute,file_system_write",
  "tags": [
    "Skills",
    "邮件",
    "提示词",
    "开发",
    "MCP"
  ],
  "source": "stepfun_log",
  "session_id": "220322022317199360",
  "user_instructions": [],
  "results": [],
  "score": 5,
  "tools_used": [
    "file_system_read",
    "email",
    "file_system_edit",
    "terminal_execute",
    "file_system_write"
  ],
  "files_touched": [
    "D://AI/",
    "D://AI//Skills//code-generation//skill.json/",
    "D://AI//Skills//data-analysis//skill.json/",
    "D://AI//MCP//10-Prompts//prompts_mcp_server.py/",
    "D://AI//Skills//document-writing//skill.json/",
    "D://AI//Skills//research//skill.json/",
    "D://AI//Skills//translation//skill.json/",
    "D://AI//Workflows//templates//code-development.json/",
    "D://AI//__build_skills.py/",
    "/python//"
  ],
  "commands": [],
  "first_time": "2026/3/10 23:21:23",
  "last_time": "2026/3/10 23:29:03",
  "task_count": 17
}
