{
  "id": "stepfun_220669015162",
  "date": "2026/3/11 22:22:21",
  "title": "阶跃AI对话 [对话]",
  "summary": "会话220669015162，3次工具调用，使用工具: terminal_execute,file_system_write",
  "tags": [
    "对话"
  ],
  "source": "stepfun_log",
  "session_id": "220669015162015744",
  "user_instructions": [],
  "results": [],
  "score": 5,
  "tools_used": [
    "terminal_execute",
    "file_system_write"
  ],
  "files_touched": [
    "D://泰拉科技//泰拉科技模组方案//_fix.py/",
    "D://泰拉科技//泰拉科技模组方案//",
    "D://泰拉科技//泰拉科技模组方案//_fix.py//",
    "D://泰拉科技//泰拉科技模组方案//_fix.py"
  ],
  "commands": [],
  "first_time": "2026/3/11 22:22:21",
  "last_time": "2026/3/11 22:23:18",
  "task_count": 3
}